README.md
setup.py
doodstream_api/__init__.py
doodstream_api/api.py
doodstream_api/baseurlscraper.py
doodstream_api.egg-info/PKG-INFO
doodstream_api.egg-info/SOURCES.txt
doodstream_api.egg-info/dependency_links.txt
doodstream_api.egg-info/not-zip-safe
doodstream_api.egg-info/requires.txt
doodstream_api.egg-info/top_level.txt