Metadata-Version: 2.1
Name: doodstream-api
Version: 0.0.5
Summary: unofficial doodstream API wrapper.
Home-page: https://github.com/adityash4rma/doodstream
Author: Aditya Sharma
Author-email: adityasharma13373@gmail.com
License: UNKNOWN
Keywords: api doodstream video hosting unlimited wrapper
Platform: UNKNOWN
Classifier: Development Status :: 5 - Production/Stable
Classifier: Programming Language :: Python :: 3
Classifier: License :: OSI Approved :: MIT License
